KNMIdata/KNMI.py
KNMIdata/KNMI_data_fetch.py
KNMIdata/__init__.py
KNMIdata/loading_screen.py
KNMIdata-1.0.2.dist-info/LICENSE.txt
KNMIdata-1.0.2.dist-info/METADATA
KNMIdata-1.0.2.dist-info/WHEEL
KNMIdata-1.0.2.dist-info/top_level.txt
KNMIdata-1.0.2.dist-info/RECORD
