Metadata-Version: 2.1
Name: KNMIdata
Version: 1.0.2
Summary: KNMI hourly data API
Home-page: https://github.com/macukadam/KNMI_weather_api
Author: Ugurcan Akpulat
Author-email: ugurcan.akpulat@gmail.com
License: UNKNOWN
Platform: UNKNOWN
Classifier: Programming Language :: Python :: 3
Classifier: License :: OSI Approved :: MIT License
Classifier: Operating System :: OS Independent
License-File: LICENSE.txt
